Metadata-Version: 1.2
Name: dtoo
Version: 0.0.6
Summary: Parse every data to python object
Home-page: UNKNOWN
Author: jdragon96
License: UNKNOWN
Platform: UNKNOWN
Classifier: Programming Language :: Python :: 3
Classifier: License :: OSI Approved :: MIT License
Classifier: Operating System :: OS Independent
Requires-Python: >=3.6
